queens8/Queens8.py
queens8/__init__.py
queens8-0.1.2.dist-info/LICENSE.txt
queens8-0.1.2.dist-info/METADATA
queens8-0.1.2.dist-info/WHEEL
queens8-0.1.2.dist-info/top_level.txt
queens8-0.1.2.dist-info/RECORD
