Metadata-Version: 2.1
Name: queens8
Version: 0.1.2
Summary: An Exploration of aspects of the eight queens problem
Home-page: https://github.com/DanLBates/queens8
Author: Daniel L. Bates
Author-email: danbates@verizon.net
License: UNKNOWN
Keywords: 'eight','queens','Wirth','Dijkstra','8Queens','dan.bates'
Platform: UNKNOWN
Classifier: Programming Language :: Python :: 3
Classifier: License :: OSI Approved :: MIT License
Classifier: Operating System :: OS Independent
Classifier: Intended Audience :: End Users/Desktop
Requires-Python: >=3.8
License-File: LICENSE.txt
